{"Nodes":[],"ExecutionTime":"2021-12-16T14:58:40.0477345Z","GenerationTime":"0001-01-01T00:00:00","PluginUserSpecFlowId":"38f6eb62-04ea-49a1-a309-4a83e82486b5","CLIUserSpecFlowId":null,"ExecutionResults":[{"ContextType":"Scenario","FeatureFolderPath":"Features","FeatureTitle":"EvideaWebUI Tests","ScenarioTitle":"Adding the product to the basket","ScenarioArguments":[],"Status":"OK","StepResults":[{"Duration":"00:00:05.4269995","Status":"OK","Error":null,"Outputs":null},{"Duration":"00:00:00.3945971","Status":"OK","Error":null,"Outputs":null},{"Duration":"00:00:02.0883701","Status":"OK","Error":null,"Outputs":null},{"Duration":"00:00:03.0559394","Status":"OK","Error":null,"Outputs":null},{"Duration":"00:00:00.2612507","Status":"OK","Error":null,"Outputs":null},{"Duration":"00:00:01.2942050","Status":"OK","Error":null,"Outputs":null},{"Duration":"00:00:00.2204786","Status":"OK","Error":null,"Outputs":null}],"Outputs":null},{"ContextType":"Scenario","FeatureFolderPath":"Features","FeatureTitle":"EvideaWebUI Tests","ScenarioTitle":"Incorrect product search in the search box","ScenarioArguments":["asdkjasdkjaksdj"],"Status":"OK","StepResults":[{"Duration":"00:00:04.5743136","Status":"OK","Error":null,"Outputs":null},{"Duration":"00:00:00.4742801","Status":"OK","Error":null,"Outputs":null},{"Duration":"00:00:00.7065773","Status":"OK","Error":null,"Outputs":null},{"Duration":"00:00:00.2899327","Status":"OK","Error":null,"Outputs":null}],"Outputs":null}],"StepReports":null}